bee_django_social_feed
