Metadata-Version: 1.0
Name: bee-django-social-feed
Version: 0.0.41
Summary: A line of description
Home-page: UNKNOWN
Author: huangwei
Author-email: imonyse@gmail.com
License: MIT
Platform: UNKNOWN
